duckit/__init__.py
duckit/batch.py
duckit/db.py
duckit/table.py
duckit/types.py
duckit-0.0.7.dist-info/LICENSE
duckit-0.0.7.dist-info/METADATA
duckit-0.0.7.dist-info/WHEEL
duckit-0.0.7.dist-info/top_level.txt
duckit-0.0.7.dist-info/RECORD
