Metadata-Version: 2.1
Name: duckit
Version: 0.0.7
Summary: Unofficial DuckDB toolkit
Home-page: https://github.com/kapily/duckit
Author: Kapil Yedidi
Author-email: kapily.code@gmail.com
License: UNKNOWN
Platform: UNKNOWN
Classifier: Programming Language :: Python :: 3
Classifier: License :: OSI Approved :: MIT License
Classifier: Operating System :: OS Independent
Requires-Python: >=3.0
Requires-Dist: duckdb (<1,>=0.2.3)
